configurave.py
configurave-0.1.2.dist-info/WHEEL
configurave-0.1.2.dist-info/METADATA
configurave-0.1.2.dist-info/RECORD
