Metadata-Version: 2.1
Name: configurave
Version: 0.1.2
Summary: A one-size-fits-all configuration scheme manager
Home-page: https://github.com/discord-modmail/configurave
Author: Bast
Author-email: bast@fastmail.com
Requires-Python: >=3.7,<4.0
Classifier: Programming Language :: Python :: 3
Classifier: Programming Language :: Python :: 3.7
Classifier: Programming Language :: Python :: 3.8
Classifier: Programming Language :: Python :: 3.9
Provides-Extra: dotenv
Requires-Dist: atoml (>=1.0.3,<2.0.0)
Requires-Dist: python-dotenv (>=0.19.0,<0.20.0); extra == "dotenv"
Project-URL: Repository, https://github.com/discord-modmail/configurave
